mira_recon/.gitignore
mira_recon/__init__.py
mira_recon/_mira_.py
mira_recon/subdomains.txt
mira_recon/modules/DomainInfo.py
mira_recon/modules/PortScanner.py
mira_recon/modules/WebScanner.py
mira_recon/modules/WebsiteAnalyzer.py
mira_recon/modules/utils.py
mira_recon-0.3.8.dist-info/entry_points.txt
mira_recon-0.3.8.dist-info/WHEEL
mira_recon-0.3.8.dist-info/METADATA
mira_recon-0.3.8.dist-info/RECORD
