Metadata-Version: 2.3
Name: mira_recon
Version: 0.3.8
Summary: A reconnaissance tool for information gathering
Keywords: reconnaissance,information gathering,security,tool
Author-email: Liam Halliden <lhallidenw@gmail.com>
Requires-Python: >=3.5
Classifier: License :: OSI Approved :: MIT License
Requires-Dist: requests
Requires-Dist: beautifulsoup4
Requires-Dist: builtwith
Requires-Dist: python-whois
Project-URL: Documentation, https://github.com/HaldenLF/Mira
Project-URL: Source, https://github.com/HaldenLF/Mira
